setup.py
ipyroute/__init__.py
ipyroute/address.py
ipyroute/base.py
ipyroute/link.py
ipyroute/neighbor.py
ipyroute/route.py
ipyroute/rule.py
ipyroute.egg-info/PKG-INFO
ipyroute.egg-info/SOURCES.txt
ipyroute.egg-info/dependency_links.txt
ipyroute.egg-info/requires.txt
ipyroute.egg-info/top_level.txt